libkosciuszko/__init__.py
libkosciuszko-0.1.3.dist-info/LICENSE
libkosciuszko-0.1.3.dist-info/METADATA
libkosciuszko-0.1.3.dist-info/WHEEL
libkosciuszko-0.1.3.dist-info/top_level.txt
libkosciuszko-0.1.3.dist-info/RECORD
