Metadata-Version: 2.1
Name: libkosciuszko
Version: 0.1.3
Summary: Library for managing kosciuszko vaults
Home-page: https://git.sr.ht/~happy_shredder
Author: happy_shredder
Author-email: contact@etage.io
License: UNKNOWN
Platform: UNKNOWN
Classifier: Programming Language :: Python :: 3
Classifier: License :: OSI Approved :: GNU General Public License v3 or later (GPLv3+)
Classifier: Operating System :: POSIX :: Linux
Classifier: Topic :: Security :: Cryptography
Requires-Python: >=3.7
